mean.py
mean-0.1.0.dist-info/LICENSE
mean-0.1.0.dist-info/WHEEL
mean-0.1.0.dist-info/METADATA
mean-0.1.0.dist-info/RECORD
